dcrx_kv/__init__.py
dcrx_kv/app.py
dcrx_kv/lifespan.py
dcrx_kv/cli/__init__.py
dcrx_kv/cli/base.py
dcrx_kv/cli/database.py
dcrx_kv/cli/server.py
dcrx_kv/context/__init__.py
dcrx_kv/context/manager.py
dcrx_kv/context/types.py
dcrx_kv/database/__init__.py
dcrx_kv/database/connection.py
dcrx_kv/database/connection_config.py
dcrx_kv/database/table_types.py
dcrx_kv/database/models/__init__.py
dcrx_kv/database/models/database_transaction_result.py
dcrx_kv/env/__init__.py
dcrx_kv/env/env.py
dcrx_kv/env/load_env.py
dcrx_kv/env/time_parser.py
dcrx_kv/middleware/__init__.py
dcrx_kv/middleware/auth_middleware.py
dcrx_kv/services/__init__.py
dcrx_kv/services/auth/__init__.py
dcrx_kv/services/auth/context.py
dcrx_kv/services/auth/manager.py
dcrx_kv/services/auth/models/__init__.py
dcrx_kv/services/auth/models/auth_claims.py
dcrx_kv/services/auth/models/auth_response.py
dcrx_kv/services/auth/models/authentication_failure_exception.py
dcrx_kv/services/auth/models/generated_token.py
dcrx_kv/services/monitoring/__init__.py
dcrx_kv/services/monitoring/context.py
dcrx_kv/services/monitoring/base/__init__.py
dcrx_kv/services/monitoring/base/exceptions.py
dcrx_kv/services/monitoring/base/monitor.py
dcrx_kv/services/monitoring/cpu/__init__.py
dcrx_kv/services/monitoring/cpu/monitor.py
dcrx_kv/services/monitoring/memory/__init__.py
dcrx_kv/services/monitoring/memory/monitor.py
dcrx_kv/services/storage/__init__.py
dcrx_kv/services/storage/connection.py
dcrx_kv/services/storage/context.py
dcrx_kv/services/storage/job.py
dcrx_kv/services/storage/queue.py
dcrx_kv/services/storage/service.py
dcrx_kv/services/storage/status.py
dcrx_kv/services/storage/clients/__init__.py
dcrx_kv/services/storage/clients/azure_blob.py
dcrx_kv/services/storage/clients/client.py
dcrx_kv/services/storage/clients/client_type.py
dcrx_kv/services/storage/clients/disk.py
dcrx_kv/services/storage/clients/google_cloud_storage.py
dcrx_kv/services/storage/clients/s3.py
dcrx_kv/services/storage/models/__init__.py
dcrx_kv-0.1.3.dist-info/LICENSE
dcrx_kv-0.1.3.dist-info/METADATA
dcrx_kv-0.1.3.dist-info/WHEEL
dcrx_kv-0.1.3.dist-info/entry_points.txt
dcrx_kv-0.1.3.dist-info/top_level.txt
dcrx_kv-0.1.3.dist-info/RECORD
